CHANGELOG
LICENSE
MANIFEST.in
README.rst
setup.py
lisense/__init__.py
lisense/lisense.py
lisense.egg-info/PKG-INFO
lisense.egg-info/SOURCES.txt
lisense.egg-info/dependency_links.txt
lisense.egg-info/entry_points.txt
lisense.egg-info/pbr.json
lisense.egg-info/requires.txt
lisense.egg-info/top_level.txt
lisense/commands/__init__.py
lisense/commands/guide.py
lisense/commands/list.py
lisense/commands/new.py
lisense/commands/setup.py
lisense/config/__init__.py
lisense/config/configer.py
lisense/data/__init__.py
lisense/data/index.py
lisense/data/metadata/agpl-3.0
lisense/data/metadata/apache-2.0
lisense/data/metadata/artistic-2.0
lisense/data/metadata/bsd-2-clause
lisense/data/metadata/bsd-3-clause
lisense/data/metadata/cc0-1.0
lisense/data/metadata/epl-1.0
lisense/data/metadata/gpl-2.0
lisense/data/metadata/gpl-3.0
lisense/data/metadata/isc
lisense/data/metadata/lgpl-2.1
lisense/data/metadata/lgpl-3.0
lisense/data/metadata/mit
lisense/data/metadata/mpl-2.0
lisense/data/metadata/no-license
lisense/data/metadata/unlicense
lisense/data/template/agpl-3.0.tmpl
lisense/data/template/apache-2.0.tmpl
lisense/data/template/artistic-2.0.tmpl
lisense/data/template/bsd-2-clause.tmpl
lisense/data/template/bsd-3-clause.tmpl
lisense/data/template/cc0-1.0.tmpl
lisense/data/template/epl-1.0.tmpl
lisense/data/template/gpl-2.0.tmpl
lisense/data/template/gpl-3.0.tmpl
lisense/data/template/isc.tmpl
lisense/data/template/lgpl-2.1.tmpl
lisense/data/template/lgpl-3.0.tmpl
lisense/data/template/mit.tmpl
lisense/data/template/mpl-2.0.tmpl
lisense/data/template/no-license.tmpl
lisense/data/template/unlicense.tmpl
lisense/parser/__init__.py
lisense/parser/parser.py