Metadata-Version: 1.1
Name: lisense
Version: 1.1.0
Summary: Sensible repository licensing for Humans
Home-page: https://github.com/pravj/lisense
Author: Pravendra Singh
Author-email: hackpravj@gmail.com
License: MIT
Keywords: git github bitbucket repository license
Platform: UNKNOWN
Classifier: Development Status :: 5 - Production/Stable
Classifier: Environment :: Console
Classifier: Operating System :: OS Independent
Classifier: Intended Audience :: Developers
Classifier: License :: OSI Approved :: MIT License
Classifier: Natural Language :: English
Classifier: Programming Language :: Python :: 2.6
Classifier: Programming Language :: Python :: 2.7
Classifier: Topic :: Software Development :: Version Control
